awslabs/__init__.py
awslabs/iam_mcp_server/__init__.py
awslabs/iam_mcp_server/aws_client.py
awslabs/iam_mcp_server/context.py
awslabs/iam_mcp_server/errors.py
awslabs/iam_mcp_server/models.py
awslabs/iam_mcp_server/server.py
awslabs_iam_mcp_server-1.0.11.dist-info/METADATA
awslabs_iam_mcp_server-1.0.11.dist-info/WHEEL
awslabs_iam_mcp_server-1.0.11.dist-info/entry_points.txt
awslabs_iam_mcp_server-1.0.11.dist-info/licenses/LICENSE
awslabs_iam_mcp_server-1.0.11.dist-info/licenses/NOTICE
awslabs_iam_mcp_server-1.0.11.dist-info/RECORD
